minigasket/__init__.py
minigasket/_core.py
minigasket/_exceptions.py
pyminigasket-0.2.0.dist-info/LICENSE
pyminigasket-0.2.0.dist-info/WHEEL
pyminigasket-0.2.0.dist-info/METADATA
pyminigasket-0.2.0.dist-info/RECORD
