Metadata-Version: 2.1
Name: pyminigasket
Version: 0.2.0
Summary: A tiny library for dataflow programming.
Home-page: https://gitlab.com/cvpines/pyminigasket
License: BSD-3-Clause
Keywords: dataflow,flow
Author: Coriander V. Pines
Author-email: contact@corianderpines.org
Requires-Python: >=3.7,<4.0
Classifier: Development Status :: 3 - Alpha
Classifier: Intended Audience :: Developers
Classifier: License :: OSI Approved :: BSD License
Classifier: Programming Language :: Python :: 3
Classifier: Programming Language :: Python :: 3.7
Classifier: Programming Language :: Python :: 3.8
Classifier: Topic :: Software Development :: Libraries
Classifier: Topic :: Software Development :: Libraries :: Application Frameworks
Classifier: Topic :: Software Development :: Libraries :: Python Modules
Project-URL: Documentation, https://gitlab.com/cvpines/pyminigasket/-/blob/stable/README.md
Project-URL: Repository, https://gitlab.com/cvpines/pyminigasket
